a_pandas_ex_bs4df/README.MD
a_pandas_ex_bs4df/__init__.py
a_pandas_ex_bs4df/requirements.txt
a_pandas_ex_bs4df/thirdparty.json
a_pandas_ex_bs4df-0.12.dist-info/LICENSE.rst
a_pandas_ex_bs4df-0.12.dist-info/METADATA
a_pandas_ex_bs4df-0.12.dist-info/WHEEL
a_pandas_ex_bs4df-0.12.dist-info/top_level.txt
a_pandas_ex_bs4df-0.12.dist-info/RECORD
