Metadata-Version: 2.1
Name: a-pandas-ex-bs4df
Version: 0.12
Summary: One-line-web-scraping by combining pandas and BeautifulSoup4
Home-page: https://github.com/hansalemaos/a_pandas_ex_bs4df
Author: Johannes Fischer
Author-email: aulasparticularesdealemaosp@gmail.com
License: MIT
Keywords: BeautifulSoup4,bs4,pandas,web scraping
Classifier: Development Status :: 4 - Beta
Classifier: Programming Language :: Python :: 3 :: Only
Classifier: Programming Language :: Python :: 3.10
Classifier: Topic :: Software Development :: Libraries :: Python Modules
Classifier: Topic :: Utilities
License-File: LICENSE.rst
Requires-Dist: beautifulsoup4
Requires-Dist: lxml
Requires-Dist: pandas
Requires-Dist: regex
Requires-Dist: requests
Requires-Dist: useful-functions-easier-life
